[
    {
        "district": "0",
        "costs-shared": 1
    },
    {
        "location": "29,36",
        "capacity": 1507.0,
        "houses": [
            {
                "location": "28,36",
                "output": "53.97543253",
                "cables": [
                    [
                        28,
                        36
                    ],
                    [
                        29,
                        36
                    ]
                ]
            },
            {
                "location": "28,37",
                "output": "53.97543253",
                "cables": [
                    [
                        28,
                        37
                    ],
                    [
                        28,
                        36
                    ],
                    [
                        29,
                        36
                    ]
                ]
            },
            {
                "location": "30,36",
                "output": "66.13020717",
                "cables": [
                    [
                        30,
                        36
                    ],
                    [
                        29,
                        36
                    ]
                ]
            },
            {
                "location": "31,33",
                "output": "66.13020717",
                "cables": [
                    [
                        31,
                        33
                    ],
                    [
                        31,
                        34
                    ],
                    [
                        31,
                        35
                    ],
                    [
                        31,
                        36
                    ],
                    [
                        30,
                        36
                    ],
                    [
                        29,
                        36
                    ]
                ]
            }
        ]
    }
]